codyssey/__init__.py
codyssey/leetcode/__init__.py
codyssey/leetcode/lc1_two_sum.py
codyssey/leetcode/lc2_add_two_numbers.py
codyssey/leetcode/lc3_longest_substring.py
codyssey/leetcode/lc4_median_soerted_arrays.py
codyssey/leetcode/lc5_longest_palindrome.py
codyssey/neetcode/__init__.py
tests/__init__.py
Codyssey-1.0.8.dist-info/LICENSE
Codyssey-1.0.8.dist-info/METADATA
Codyssey-1.0.8.dist-info/WHEEL
Codyssey-1.0.8.dist-info/top_level.txt
Codyssey-1.0.8.dist-info/RECORD
