Metadata-Version: 2.1
Name: Codyssey
Version: 1.0.8
Summary: Python arsenal for competitive mastery
Home-page: https://github.com/varskann/Codyssey
Author: Kanishk Varshney
Author-email: varskann1993@gmail.com
Classifier: Programming Language :: Python :: 3
Classifier: License :: OSI Approved :: MIT License
Classifier: Operating System :: OS Independent
License-File: LICENSE
Requires-Dist: typing
Requires-Dist: typing-extensions
